bdlogging/__init__.py
bdlogging/handlers.py
bdlogging-0.0.10.dist-info/METADATA
bdlogging-0.0.10.dist-info/WHEEL
bdlogging-0.0.10.dist-info/top_level.txt
bdlogging-0.0.10.dist-info/RECORD
