Metadata-Version: 2.1
Name: bdlogging
Version: 0.0.10
Summary: RabbitMQログ出力モジュール
Home-page: https://gitlab.com/belldata/logging.git
Author: nozomi.nishinohara
Author-email: nozomi.nishinohara@belldata.co.jp
License: UNKNOWN
Platform: UNKNOWN
Classifier: Programming Language :: Python :: 3.6
Classifier: Programming Language :: Python :: 3.7
Requires-Dist: pika
